xero_agent_toolkit/__init__.py
xero_agent_toolkit/xero_agent_toolkit.py
xero_agent_toolkit/xero_api_calls.py
xero_agent_toolkit-0.0.5.dist-info/METADATA
xero_agent_toolkit-0.0.5.dist-info/WHEEL
xero_agent_toolkit-0.0.5.dist-info/licenses/LICENSE
xero_agent_toolkit-0.0.5.dist-info/RECORD
