Metadata-Version: 2.4
Name: xero-agent-toolkit
Version: 0.0.5
Summary: A Xero toolkit for AI agents
Author-email: reizenband <reizenband@gmail.com>
License-File: LICENSE
Classifier: License :: OSI Approved :: MIT License
Classifier: Operating System :: OS Independent
Classifier: Programming Language :: Python :: 3
Requires-Python: >=3.8
